{
  "hash": "37979863e68ad32a52c846cff2df9a2a",
  "result": {
    "engine": "knitr",
    "markdown": "---\ntitle: \"Publishing Quarto with R, Python, and Julia\"\ndescription: \"An example for a Quarto document that contains output from R, Python, and Julia code\"\nmetadata:\n  pagetitle: \"Publishing Quarto with R, Python, and Julia\"\nauthor: \"Christoph Scheuch\"\ndate: \"2024-01-11\" \nimage: thumbnail.png\nimage-alt: ... Created with DALL-E 3.\ndraft: true\n---\n\n\n\n`knitr` uses `reticulate` to execute Python code and `JuliaCall` to run Julia code...\n\n\nSet-up:\n\n- `renv` to manage R packages\n- `renv` & `reticulate` to manage Python libraries\n- use command line to initialize project to record / restore toml files\n\n\n\n::: {.cell}\n\n```{.r .cell-code}\n# Note that this code chunk is only required because of a bug with JuliaCall that prevents julia_setup() from finding the installation: https://github.com/quarto-dev/quarto-cli/issues/7055\nJuliaCall::julia_setup(\"/Applications/Julia-1.9.app/Contents/Resources/julia/bin/\")\n```\n:::\n\n\n\n...\n\n::: {.panel-tabset}\n### R\n\n::: {.cell}\n\n```{.r .cell-code}\nlibrary(dplyr)\nlibrary(palmerpenguins)\n\npenguins <- palmerpenguins::penguins\n\npenguins\n```\n\n::: {.cell-output .cell-output-stdout}\n\n```\n# A tibble: 344 × 8\n   species island    bill_length_mm bill_depth_mm flipper_length_mm body_mass_g\n   <fct>   <fct>              <dbl>         <dbl>             <int>       <int>\n 1 Adelie  Torgersen           39.1          18.7               181        3750\n 2 Adelie  Torgersen           39.5          17.4               186        3800\n 3 Adelie  Torgersen           40.3          18                 195        3250\n 4 Adelie  Torgersen           NA            NA                  NA          NA\n 5 Adelie  Torgersen           36.7          19.3               193        3450\n 6 Adelie  Torgersen           39.3          20.6               190        3650\n 7 Adelie  Torgersen           38.9          17.8               181        3625\n 8 Adelie  Torgersen           39.2          19.6               195        4675\n 9 Adelie  Torgersen           34.1          18.1               193        3475\n10 Adelie  Torgersen           42            20.2               190        4250\n# ℹ 334 more rows\n# ℹ 2 more variables: sex <fct>, year <int>\n```\n\n\n:::\n:::\n\n### Python\n\n::: {.cell}\n\n```{.python .cell-code}\nimport pandas as pd\nfrom palmerpenguins import load_penguins\n\npenguins = load_penguins()\n\npenguins\n```\n\n::: {.cell-output .cell-output-stdout}\n\n```\n       species     island  bill_length_mm  ...  body_mass_g     sex  year\n0       Adelie  Torgersen            39.1  ...       3750.0    male  2007\n1       Adelie  Torgersen            39.5  ...       3800.0  female  2007\n2       Adelie  Torgersen            40.3  ...       3250.0  female  2007\n3       Adelie  Torgersen             NaN  ...          NaN     NaN  2007\n4       Adelie  Torgersen            36.7  ...       3450.0  female  2007\n..         ...        ...             ...  ...          ...     ...   ...\n339  Chinstrap      Dream            55.8  ...       4000.0    male  2009\n340  Chinstrap      Dream            43.5  ...       3400.0  female  2009\n341  Chinstrap      Dream            49.6  ...       3775.0    male  2009\n342  Chinstrap      Dream            50.8  ...       4100.0    male  2009\n343  Chinstrap      Dream            50.2  ...       3775.0  female  2009\n\n[344 rows x 8 columns]\n```\n\n\n:::\n:::\n\n### Julia\n\n::: {.cell}\n\n```{.julia .cell-code}\nusing TidierData\nusing PalmerPenguins\n\npenguins = DataFrame(PalmerPenguins.load())\n```\n\n::: {.cell-output .cell-output-stdout}\n\n```\n344×7 DataFrame\n Row │ species    island     bill_length_mm  bill_depth_mm  flipper_length_mm  ⋯\n     │ String15   String15   Float64?        Float64?       Int64?             ⋯\n─────┼──────────────────────────────────────────────────────────────────────────\n   1 │ Adelie     Torgersen            39.1           18.7                181  ⋯\n   2 │ Adelie     Torgersen            39.5           17.4                186\n   3 │ Adelie     Torgersen            40.3           18.0                195\n   4 │ Adelie     Torgersen       missing        missing              missing\n   5 │ Adelie     Torgersen            36.7           19.3                193  ⋯\n   6 │ Adelie     Torgersen            39.3           20.6                190\n   7 │ Adelie     Torgersen            38.9           17.8                181\n   8 │ Adelie     Torgersen            39.2           19.6                195\n  ⋮  │     ⋮          ⋮            ⋮               ⋮                ⋮          ⋱\n 338 │ Chinstrap  Dream                46.8           16.5                189  ⋯\n 339 │ Chinstrap  Dream                45.7           17.0                195\n 340 │ Chinstrap  Dream                55.8           19.8                207\n 341 │ Chinstrap  Dream                43.5           18.1                202\n 342 │ Chinstrap  Dream                49.6           18.2                193  ⋯\n 343 │ Chinstrap  Dream                50.8           19.0                210\n 344 │ Chinstrap  Dream                50.2           18.7                198\n                                                  2 columns and 329 rows omitted\n```\n\n\n:::\n:::\n\n:::\n\n## Conclusion\n\n...\n",
    "supporting": [],
    "filters": [
      "rmarkdown/pagebreak.lua"
    ],
    "includes": {},
    "engineDependencies": {},
    "preserve": {},
    "postProcess": true
  }
}